aidge_core/utils.py
aidge_core/scheduling.py
aidge_core/show_graphview.py
aidge_core/mem_info.py
aidge_core/dynamic_analysis.py
aidge_core/simplify_graph.py
aidge_core/__init__.py
aidge_core/static_analysis.py
aidge_core/aidge_core.cpython-311-x86_64-linux-gnu.so
aidge_core/export_utils/node_export.py
aidge_core/export_utils/export_utils.py
aidge_core/export_utils/tensor_export.py
aidge_core/export_utils/code_generation.py
aidge_core/export_utils/__init__.py
aidge_core/export_utils/data_conversion.py
aidge_core/export_utils/export_registry.py
aidge_core/export_utils/generate_main.py
aidge_core/export_utils/scheduler_export.py
aidge_core/export_utils/templates/main_benchmark_inference_time.jinja
aidge_core/export_utils/templates/main.jinja
aidge_core/export_utils/templates/forward.jinja
aidge_core/export_utils/templates/c_data.jinja
aidge_core/export_utils/templates/forward_header.jinja
aidge_core/export_utils/templates/main_benchmark_display_output.jinja
aidge_core/export_utils/templates/main_compare.jinja
aidge_core/unit_tests/test_operator_binding.py
aidge_core/unit_tests/test_tensor_scalar.py
aidge_core/unit_tests/test_parameters.py
aidge_core/unit_tests/test_output_wise_comparison.py
aidge_core/unit_tests/test_tensor.py
aidge_core/unit_tests/test_forward_dims_constant_shape.py
aidge_core/unit_tests/test_recipes.py
aidge_core/unit_tests/test_download_file.py
aidge_core/unit_tests/test_operator_squeeze.py
aidge_core/unit_tests/test_export.py
aidge_core/unit_tests/test_topological_order.py
aidge_core/unit_tests/test_impl.py
aidge_core/unit_tests/test_forwardDType.py
aidge_core/unit_tests/test_show_graphview.py
aidge_core/unit_tests/test_naming.py
aidge_core/unit_tests/test_operator_unsqueeze.py
aidge_core/benchmark/tree_structure.py
aidge_core/benchmark/logger.py
aidge_core/benchmark/benchmark_torch.py
aidge_core/benchmark/generate_graph.py
aidge_core/benchmark/output_wise_comparison.py
aidge_core-0.8.1.dist-info/entry_points.txt
aidge_core-0.8.1.dist-info/RECORD
aidge_core-0.8.1.dist-info/top_level.txt
aidge_core-0.8.1.dist-info/METADATA
aidge_core-0.8.1.dist-info/WHEEL
aidge_core-0.8.1.dist-info/licenses/LICENSE
