Metadata-Version: 2.4
Name: aidge_core
Version: 0.8.1
Summary: Core algorithms for operators and graph of the AIDGE framework
License: Eclipse Public License - v 2.0
Project-URL: Homepage, https://www.deepgreen.ai/en/platform
Project-URL: Documentation, https://eclipse.dev/aidge/
Project-URL: Repository, https://gitlab.eclipse.org/eclipse/aidge/aidge_core
Project-URL: Issues, https://gitlab.eclipse.org/eclipse/aidge/aidge_core/-/issues/
Project-URL: Changelog, https://gitlab.eclipse.org/eclipse/aidge/aidge_core/-/releases
Classifier: Development Status :: 2 - Pre-Alpha
Classifier: Programming Language :: Python :: 3
Requires-Python: >=3.10
License-File: LICENSE
Requires-Dist: numpy>=1.21.6
Requires-Dist: Jinja2>=3.1.2
Requires-Dist: matplotlib
Requires-Dist: tqdm
Requires-Dist: requests
Requires-Dist: rich
Provides-Extra: test
Requires-Dist: pytest; extra == "test"
Dynamic: license-file
